{
    "id": "skin_68824c3d5bd40",
    "skinName": "fick",
    "authorName": "Saya",
    "tags": [
        ""
    ],
    "mainCategory": "Shotgun",
    "subCategory": "Saiga-12K",
    "uploadTimestamp": 1753369661,
    "previewUrl": "https:\/\/raw.githubusercontent.com\/SkinForgeDE\/SkinForge\/main\/_previews\/skin_68824c3d5bd40.jpg",
    "files": [
        {
            "source": "brickwall004a.vmt",
            "destination": "materials\/models\/weapons\/v_models\/saiga12k\/grip.vmt"
        }
    ],
    "baseFolder": "_files\/fick_skin_68824c3d5bd40"
}