{
    "id": "skin_6883328435ca5",
    "skinName": "BW Ak-101",
    "authorName": "Paid",
    "authorSteamId": "76561198819152014",
    "tags": [
        "Black&White"
    ],
    "mainCategory": "Assault Rifle",
    "subCategory": "AK-101",
    "uploadTimestamp": 1753428612,
    "previewUrl": "https:\/\/raw.githubusercontent.com\/SkinForgeDE\/SkinForge\/main\/_previews\/skin_6883328435ca5.png",
    "files": [
        {
            "source": "materials_models_weapons_ak_101_material_#25_vmt_0.vmt",
            "destination": "materials\/models\/weapons\/ak_101\/material_#25.vmt"
        },
        {
            "source": "materials_models_weapons_ak_101_body_ak74m_vtf_1.vtf",
            "destination": "materials\/models\/weapons\/ak_101\/body_ak74m.vtf"
        },
        {
            "source": "materials_models_weapons_ak_101_body_ak74m_vtf_2.vtf",
            "destination": "materials\/models\/weapons\/ak_101\/body_ak74m.vtf"
        }
    ],
    "baseFolder": "_files\/Paid_BW-Ak-101_skin_6883328435ca5",
    "totalRating": 4,
    "ratingCount": 2,
    "averageRating": 5,
    "raters": [
        "76561198885428569"
    ],
    "ratings": {
        "76561198885428569": 5,
        "76561198819152014": 5
    },
    "likers": [
        "76561198885428569"
    ],
    "likeCount": 1,
    "favoriters": [
        "76561198885428569"
    ],
    "favoriteCount": 1,
    "downloadCount": 39
}